abx_plugin_favicon/__init__.py
abx_plugin_favicon/actors.py
abx_plugin_favicon/config.py
abx_plugin_favicon/extractors.py
abx_plugin_favicon/favicon.py
abx_plugin_favicon/models.py
abx_plugin_favicon-2024.10.28.dist-info/METADATA
abx_plugin_favicon-2024.10.28.dist-info/WHEEL
abx_plugin_favicon-2024.10.28.dist-info/entry_points.txt
abx_plugin_favicon-2024.10.28.dist-info/RECORD
